ethereum_kms_signer/__init__.py
ethereum_kms_signer/cli.py
ethereum_kms_signer/kms.py
ethereum_kms_signer/spki.py
ethereum_kms_signer-0.1.6.dist-info/entry_points.txt
ethereum_kms_signer-0.1.6.dist-info/LICENSE
ethereum_kms_signer-0.1.6.dist-info/WHEEL
ethereum_kms_signer-0.1.6.dist-info/METADATA
ethereum_kms_signer-0.1.6.dist-info/RECORD
