Metadata-Version: 2.1
Name: ethereum-kms-signer
Version: 0.1.6
Summary: Sign ETH transactions with keys stored in AWS KMS.
Home-page: https://github.com/meetmangukiya/ethereum_kms_signer
License: MIT
Author: Meet Mangukiya
Author-email: meet@flamy.dev
Requires-Python: >=3.6.1,<4.0
Classifier: Development Status :: 2 - Pre-Alpha
Classifier: Intended Audience :: Developers
Classifier: License :: OSI Approved :: MIT License
Classifier: Natural Language :: English
Classifier: Programming Language :: Python :: 3
Classifier: Programming Language :: Python :: 3.10
Classifier: Programming Language :: Python :: 3.6
Classifier: Programming Language :: Python :: 3.7
Classifier: Programming Language :: Python :: 3.8
Classifier: Programming Language :: Python :: 3.9
Provides-Extra: actions
Provides-Extra: dev
Provides-Extra: doc
Provides-Extra: test
Requires-Dist: boto3 (>=1.5.12,<2.0.0)
Requires-Dist: boto3-stubs[kms] (>=1.18.50,<2.0.0)
Requires-Dist: eth-account (>=0.5.6,<0.6.0)
Requires-Dist: eth-utils (>=1.10.0,<2.0.0)
Requires-Dist: fire (==0.4.0)
Requires-Dist: hexbytes (>=0.2.2,<0.3.0)
Requires-Dist: pyasn1 (>=0.4.8,<0.5.0)
Requires-Dist: pycryptodome (>=3.10.1,<4.0.0)
Requires-Dist: toolz (>=0.11.1,<0.12.0)
